Metadata-Version: 2.1
Name: onnsc
Version: 0.0.2
Summary: Convenience Python module for Trend Micro Smart Check
Home-page: https://onnsc.oznetnerd.com
Author: Will Robinson
Author-email: will@oznetnerd.com
License: UNKNOWN
Platform: UNKNOWN
